{
  "title": "Basic FFT MicroSim",
  "description": "A basic demonstration of FFT with time domain visualization on the top and frequency domain on the bottom, featuring adjustable frequency and amplitude controls.",
  "creator": "Dan McCreary",
  "date": "2024-07-23",
  "subject": ["Signal Processing", "FFT", "Fourier Transform", "Frequency Analysis"],
  "type": "Interactive Simulation",
  "format": "text/html",
  "language": "en",
  "rights": "CC BY-NC-SA 4.0",
  "identifier": "https://dmccreary.github.io/signal-processing/sims/fft-basic/",
  "publisher": "Dan McCreary",
  "educationalLevel": "College Freshman",
  "learningResourceType": "simulation",
  "audience": "Students, Educators",
  "version": "1.0.0",
  "bloomLevel": ["Understand", "Apply", "Analyze"],
  "concepts": [
    "Fast Fourier Transform",
    "Time domain",
    "Frequency domain",
    "Sine waves",
    "Amplitude",
    "Frequency"
  ],
  "prerequisites": [
    "Basic trigonometry",
    "Familiarity with sine waves"
  ],
  "library": "p5.js"
}
